my_funniest/__init__.py
my_funniest/text.py
my_funniest-0.1.dist-info/DESCRIPTION.rst
my_funniest-0.1.dist-info/METADATA
my_funniest-0.1.dist-info/RECORD
my_funniest-0.1.dist-info/WHEEL
my_funniest-0.1.dist-info/metadata.json
my_funniest-0.1.dist-info/top_level.txt
