Metadata-Version: 2.0
Name: my-funniest
Version: 0.1
Summary: The funniest joke in the world
Home-page: http://github.com/storborg/funniest
Author: Bram Vernaas
Author-email: amavermaas@gmail.com
License: MIT
Platform: UNKNOWN
Requires-Dist: markdown
